setup.py
distri_aws_udacity/Binomialdistribution.py
distri_aws_udacity/Gaussiandistribution.py
distri_aws_udacity/Generaldistribution.py
distri_aws_udacity/__init__.py
distri_aws_udacity.egg-info/PKG-INFO
distri_aws_udacity.egg-info/SOURCES.txt
distri_aws_udacity.egg-info/dependency_links.txt
distri_aws_udacity.egg-info/not-zip-safe
distri_aws_udacity.egg-info/top_level.txt