Metadata-Version: 1.0
Name: distri-aws-udacity
Version: 1.0
Summary: Gaussian and Binomial distributions
Home-page: UNKNOWN
Author: Utkarsh Gupta
Author-email: utkarshgupt2000@gmail.com
License: UNKNOWN
Platform: UNKNOWN
